datapungi_fed/__init__.py
datapungi_fed/api.py
datapungi_fed/driverCore.py
datapungi_fed/drivers.py
datapungi_fed/generalSettings.py
datapungi_fed/utils.py
datapungi_fed/.vscode/settings.json
datapungi_fed/config/__init__.py
datapungi_fed/config/datasetlist.yaml
datapungi_fed/config/pkgConfig.yaml
datapungi_fed/config/userSettings.json
datapungi_fed/tests/__init__.py
datapungi_fed/tests/conftest.py
datapungi_fed/tests/main.py
datapungi_fed/tests/test_drivers.py
datapungi_fed/tests/test_driversCI.py
datapungi_fed-0.3.1.dist-info/LICENSE
datapungi_fed-0.3.1.dist-info/WHEEL
datapungi_fed-0.3.1.dist-info/METADATA
datapungi_fed-0.3.1.dist-info/RECORD
