Metadata-Version: 2.1
Name: datapungi_fed
Version: 0.3.1
Summary: Gets FRED and GeoFRED data from Federal Reserve (FED) by connecting to its API.
Home-page: https://github.com/jjotterson/datapungi_fed
License: UNKNOWN
Author: James Otterson
Author-email: jjotterson@gmail.com
Classifier: License :: OSI Approved :: MIT License
Classifier: Development Status :: 4 - Beta
Classifier: Intended Audience :: Developers
Classifier: Intended Audience :: Science/Research
Classifier: Programming Language :: Python
Classifier: Programming Language :: Python :: 3.6
Classifier: Programming Language :: Python :: 3.7
Requires-Dist: requests
Requires-Dist: pandas
Requires-Dist: pytest
Requires-Dist: pytest-html
Requires-Dist: pyperclip
Requires-Dist: lxml
Requires-Dist: xlrd
Requires-Dist: beautifulsoup4
Requires-Dist: html5lib
Requires-Dist: pyyaml
